rtbold/__init__.py
rtbold/__version__.py
rtbold/processor.py
rtbold/volreg.py
rtbold/plotter/__init__.py
rtbold/plotter/dash.py
rtbold/plotter/matplotlib.py
rtbold/watcher/__init__.py
rtbold/watcher/dicom.py
rtbold/watcher/directory.py
rtbold-0.0.8.data/scripts/start.py
rtbold-0.0.8.dist-info/METADATA
rtbold-0.0.8.dist-info/WHEEL
rtbold-0.0.8.dist-info/top_level.txt
rtbold-0.0.8.dist-info/RECORD
