Metadata-Version: 2.1
Name: rtbold
Version: 0.0.8
Summary: Real Time Bold Motion Plotting
Home-page: https://github.com/harvard-nrg/rtbold
Author: Neuroinformatics Research Group
Author-email: info@neuroinfo.org
Requires-Dist: dash
Requires-Dist: pydicom
Requires-Dist: PyPubSub
Requires-Dist: watchdog
Requires-Dist: numpy
Requires-Dist: sortedcontainers
Requires-Dist: plotly
Requires-Dist: pandas
Requires-Dist: retry
